bacformer/__init__.py
bacformer/modeling/__init__.py
bacformer/modeling/argparser.py
bacformer/modeling/config.py
bacformer/modeling/data_reader.py
bacformer/modeling/modeling_base.py
bacformer/modeling/modeling_large.py
bacformer/modeling/modeling_pretraining.py
bacformer/modeling/modeling_tasks.py
bacformer/modeling/run_pretraining.py
bacformer/modeling/trainer.py
bacformer/modeling/utils.py
bacformer/pp/__init__.py
bacformer/pp/download.py
bacformer/pp/embed_prot_seqs.py
bacformer/pp/preprocess.py
bacformer/tl/__init__.py
bacformer/tl/clustering.py
bacformer/tl/operon_prediction.py
bacformer/tl/scalable_search.py
bacformer-0.2.0.dist-info/METADATA
bacformer-0.2.0.dist-info/WHEEL
bacformer-0.2.0.dist-info/licenses/LICENSE
bacformer-0.2.0.dist-info/RECORD
