Metadata-Version: 2.4
Name: bacformer
Version: 0.2.0
Summary: Modeling bacterial genomes.
Project-URL: Documentation, https://bacformer.readthedocs.io/
Project-URL: Homepage, https://github.com/macwiatrak/Bacformer
Project-URL: Source, https://github.com/macwiatrak/Bacformer
Author: Maciej Wiatrak
Maintainer-email: Maciej Wiatrak <macwiatrak@gmail.com>
License-Expression: Apache-2.0
License-File: LICENSE
Keywords: bacteria,bioinformatics,genomics,prokaryotes,transformers
Classifier: Development Status :: 3 - Alpha
Classifier: Intended Audience :: Science/Research
Classifier: License :: OSI Approved :: Apache Software License
Classifier: Operating System :: OS Independent
Classifier: Programming Language :: Python :: 3 :: Only
Classifier: Programming Language :: Python :: 3.10
Classifier: Programming Language :: Python :: 3.11
Classifier: Programming Language :: Python :: 3.12
Classifier: Programming Language :: Python :: 3.13
Classifier: Topic :: Scientific/Engineering :: Bio-Informatics
Requires-Python: >=3.10
Requires-Dist: accelerate>=0.28
Requires-Dist: biopython>=1.83
Requires-Dist: dataclasses-json>=0.6.1
Requires-Dist: datasets>=2.21
Requires-Dist: einops
Requires-Dist: hf-xet>=1.0.5
Requires-Dist: igraph>=0.11.8
Requires-Dist: leidenalg~=0.10.2
Requires-Dist: pandas>=2.2.3
Requires-Dist: pyarrow>=19.0.1
Requires-Dist: scanpy>=1.11.1
Requires-Dist: session-info
Requires-Dist: tensorboardx>=2.6.2
Requires-Dist: torch>=2.5.1
Requires-Dist: torchmetrics>=1.7.1
Requires-Dist: transformers>=4.38.2
Requires-Dist: typed-argument-parser>=1.8.1
Provides-Extra: dev
Requires-Dist: pre-commit; extra == 'dev'
Requires-Dist: twine>=4.0.2; extra == 'dev'
Provides-Extra: docs
Requires-Dist: docutils!=0.18.*,!=0.19.*,>=0.8; extra == 'docs'
Requires-Dist: ipykernel; extra == 'docs'
Requires-Dist: ipython; extra == 'docs'
Requires-Dist: myst-nb>=1.1; extra == 'docs'
Requires-Dist: pandas; extra == 'docs'
Requires-Dist: setuptools; extra == 'docs'
Requires-Dist: sphinx-autodoc-typehints; extra == 'docs'
Requires-Dist: sphinx-book-theme>=1; extra == 'docs'
Requires-Dist: sphinx-copybutton; extra == 'docs'
Requires-Dist: sphinx-tabs; extra == 'docs'
Requires-Dist: sphinx>=4; extra == 'docs'
Requires-Dist: sphinxcontrib-bibtex>=1; extra == 'docs'
Requires-Dist: sphinxext-opengraph; extra == 'docs'
Provides-Extra: faesm
Requires-Dist: faesm[flash-attn]>=0.1.1; extra == 'faesm'
Requires-Dist: flash-attn>=0.2; extra == 'faesm'
Provides-Extra: faiss
Requires-Dist: faiss-cpu; extra == 'faiss'
Provides-Extra: notebook
Requires-Dist: ipywidgets; extra == 'notebook'
Requires-Dist: jupyterlab; extra == 'notebook'
Provides-Extra: test
Requires-Dist: coverage; extra == 'test'
Requires-Dist: pytest; extra == 'test'
